django_yubin/__init__.py
django_yubin/admin.py
django_yubin/apps.py
django_yubin/backends.py
django_yubin/constants.py
django_yubin/engine.py
django_yubin/mailparser_utils.py
django_yubin/message_views.py
django_yubin/models.py
django_yubin/settings.py
django_yubin/signals.py
django_yubin/storage_backends.py
django_yubin/tasks.py
django_yubin/urls.py
django_yubin/version.py
django_yubin/views.py
django_yubin/management/__init__.py
django_yubin/management/commands/__init__.py
django_yubin/management/commands/create_mail.py
django_yubin/management/commands/db2file.py
django_yubin/management/commands/file2db.py
django_yubin/management/commands/sample.pdf
django_yubin/management/commands/send_test_mail.py
django_yubin/migrations/0001_initial.py
django_yubin/migrations/0002_auto_20170405_1635.py
django_yubin/migrations/0003_auto_20171201_1506.py
django_yubin/migrations/0004_message_date_sent.py
django_yubin/migrations/0005_auto_20181128_0407.py
django_yubin/migrations/0006_auto_20200319_1120.py
django_yubin/migrations/0007_auto_20200319_1158.py
django_yubin/migrations/0008_auto_20200320_0407.py
django_yubin/migrations/0009_auto_20221122_1605.py
django_yubin/migrations/0010_message_storage.py
django_yubin/migrations/0011_message_bcc_address_message_cc_address_and_more.py
django_yubin/migrations/0012_alter_blacklist_id_alter_log_id_alter_message_id.py
django_yubin/migrations/__init__.py
django_yubin/templates/admin/django_yubin/message/change_form.html
django_yubin/templates/django_yubin/html_detail.html
django_yubin/templates/django_yubin/message_detail.html
django_yubin-2.0.6.dist-info/licenses/LICENSE
django_yubin-2.0.6.dist-info/METADATA
django_yubin-2.0.6.dist-info/WHEEL
django_yubin-2.0.6.dist-info/top_level.txt
django_yubin-2.0.6.dist-info/RECORD
